MANIFEST.in
README.rst
setup.cfg
setup.py
ckanext/__init__.py
ckanext/govdf_theme/__init__.py
ckanext/govdf_theme/plugin.py
ckanext/govdf_theme/fanstatic/bootstrap.js
ckanext/govdf_theme/fanstatic/style.js
ckanext/govdf_theme/less/ckan_main.less
ckanext/govdf_theme/less/gdf_main.less
ckanext/govdf_theme/less/gdf_ui.less
ckanext/govdf_theme/less/govdf_theme.less
ckanext/govdf_theme/less/style.less
ckanext/govdf_theme/less/style_desktop.less
ckanext/govdf_theme/less/style_tablet.less
ckanext/govdf_theme/less/theme_acessivel.less
ckanext/govdf_theme/less/bootstrap/mixins.less
ckanext/govdf_theme/less/bootstrap/mixins/alerts.less
ckanext/govdf_theme/less/bootstrap/mixins/background-variant.less
ckanext/govdf_theme/less/bootstrap/mixins/border-radius.less
ckanext/govdf_theme/less/bootstrap/mixins/buttons.less
ckanext/govdf_theme/less/bootstrap/mixins/center-block.less
ckanext/govdf_theme/less/bootstrap/mixins/clearfix.less
ckanext/govdf_theme/less/bootstrap/mixins/forms.less
ckanext/govdf_theme/less/bootstrap/mixins/gradients.less
ckanext/govdf_theme/less/bootstrap/mixins/grid-framework.less
ckanext/govdf_theme/less/bootstrap/mixins/grid.less
ckanext/govdf_theme/less/bootstrap/mixins/hide-text.less
ckanext/govdf_theme/less/bootstrap/mixins/image.less
ckanext/govdf_theme/less/bootstrap/mixins/labels.less
ckanext/govdf_theme/less/bootstrap/mixins/list-group.less
ckanext/govdf_theme/less/bootstrap/mixins/nav-divider.less
ckanext/govdf_theme/less/bootstrap/mixins/nav-vertical-align.less
ckanext/govdf_theme/less/bootstrap/mixins/opacity.less
ckanext/govdf_theme/less/bootstrap/mixins/pagination.less
ckanext/govdf_theme/less/bootstrap/mixins/panels.less
ckanext/govdf_theme/less/bootstrap/mixins/progress-bar.less
ckanext/govdf_theme/less/bootstrap/mixins/reset-filter.less
ckanext/govdf_theme/less/bootstrap/mixins/reset-text.less
ckanext/govdf_theme/less/bootstrap/mixins/resize.less
ckanext/govdf_theme/less/bootstrap/mixins/responsive-visibility.less
ckanext_govdf_theme.egg-info/PKG-INFO
ckanext_govdf_theme.egg-info/SOURCES.txt
ckanext_govdf_theme.egg-info/dependency_links.txt
ckanext_govdf_theme.egg-info/entry_points.txt
ckanext_govdf_theme.egg-info/pbr.json
ckanext_govdf_theme.egg-info/top_level.txt