Metadata-Version: 1.1
Name: ckanext-govdf-theme
Version: 0.0.8.6.2
Summary: The Brasília Government Theme for Opandata
Home-page: https://lucas_jlma@bitbucket.org/lucas_jlma/gdf_ckan_theme.git
Author: Lucas Amaral
Author-email: lucas_jlma@hotmail.com
License: AGPL
Keywords: CKAN GDF
Platform: UNKNOWN
Classifier: Development Status :: 4 - Beta
Classifier: License :: OSI Approved :: GNU Affero General Public License v3 or later (AGPLv3+)
Classifier: Programming Language :: Python :: 2.6
Classifier: Programming Language :: Python :: 2.7
